atomicl/_py.py
atomicl/_atomic.h
atomicl/_structure.py
atomicl/_compat.py
atomicl/_atomic.c
atomicl/_cy.cpython-34m.so
atomicl/_cy.c
atomicl/__init__.py
atomicl/_cy.pyx
atomicl/_catomic.pxd
atomicl-0.1.1.dist-info/LICENSE.txt
atomicl-0.1.1.dist-info/top_level.txt
atomicl-0.1.1.dist-info/RECORD
atomicl-0.1.1.dist-info/METADATA
atomicl-0.1.1.dist-info/WHEEL
