Metadata-Version: 1.2
Name: atomicl
Version: 0.1.1
Summary: Yet another implementation of AtomicLong
Home-page: https://github.com/gagoman/atomicl
Author: Alex Khomchenko
Author-email: akhomchenko@gmail.com
License: MIT
Keywords: atomiclong
Platform: UNKNOWN
Classifier: Development Status :: 3 - Alpha
Classifier: Intended Audience :: Developers
Classifier: License :: OSI Approved :: MIT License
Classifier: Programming Language :: Python :: 3
Classifier: Programming Language :: Python :: 3.4
Classifier: Programming Language :: Python :: 3.5
Classifier: Programming Language :: Python :: 3.6
Classifier: Programming Language :: Python :: 3.7
Requires-Python: ~=3.4
